py_probe_mapper/__init__.py
py_probe_mapper/cli.py
py_probe_mapper/sdk.py
py_probe_mapper/accession_lookup/__init__.py
py_probe_mapper/accession_lookup/accession_lookup.py
py_probe_mapper/coordinate_lookup/__init__.py
py_probe_mapper/coordinate_lookup/coordinate_lookup.py
py_probe_mapper/direct_lookup/__init__.py
py_probe_mapper/direct_lookup/direct_lookup.py
py_probe_mapper/genome_utils/Homo_sapiens.GRCh38.genes.tsv
py_probe_mapper/lookup_classifier/__init__.py
py_probe_mapper/lookup_classifier/gpt_lookup_classifier.py
py_probe_mapper/lookup_classifier/optimised_lookup_classifier.py
py_probe_mapper/metadata_builder/__init_.py
py_probe_mapper/metadata_builder/build_metadata.py
py_probe_mapper-0.1.0.dist-info/licenses/LICENSE
py_probe_mapper-0.1.0.dist-info/METADATA
py_probe_mapper-0.1.0.dist-info/WHEEL
py_probe_mapper-0.1.0.dist-info/entry_points.txt
py_probe_mapper-0.1.0.dist-info/top_level.txt
py_probe_mapper-0.1.0.dist-info/RECORD
