Metadata-Version: 2.4
Name: py_probe_mapper
Version: 0.1.0
Summary: A lightweight Python package for mapping GEO platform probes to their corresponding gene identifiers in seconds!
Author-email: Swapnonil Chakraborty <swapnonil0007@gmail.com>
License-Expression: AGPL-3.0
Requires-Python: >=3.12
License-File: LICENSE
Requires-Dist: aiohttp>=3.12.15
Requires-Dist: huggingface-hub>=0.34.4
Requires-Dist: jinja2>=3.1.6
Requires-Dist: numpy>=2.3.2
Requires-Dist: pandas>=2.3.1
Requires-Dist: python-dotenv>=1.1.1
Requires-Dist: questionary>=2.1.0
Requires-Dist: requests>=2.32.4
Requires-Dist: tenacity>=9.1.2
Requires-Dist: tqdm>=4.67.1
Requires-Dist: zarr>=3.1.1
Dynamic: license-file
